numofdicerolls/__init__.py
numofdicerolls/dice_roll.py
numofdicerolls-2.75.dist-info/METADATA
numofdicerolls-2.75.dist-info/WHEEL
numofdicerolls-2.75.dist-info/top_level.txt
numofdicerolls-2.75.dist-info/RECORD
