Metadata-Version: 2.1
Name: numofdicerolls
Version: 2.75
Summary: Python script from pipline
Home-page: UNKNOWN
Author: Dean
Author-email: <dneugebauer@live.com>
License: UNKNOWN
Keywords: python
Platform: UNKNOWN
Classifier: Development Status :: 1 - Planning
Classifier: Intended Audience :: Developers
Classifier: Programming Language :: Python :: 3
Classifier: Operating System :: Unix
Classifier: Operating System :: MacOS :: MacOS X
Classifier: Operating System :: Microsoft :: Windows
